MANIFEST.in
README.rst
setup.py
metamon/__init__.py
metamon/functions.py
metamon.egg-info/PKG-INFO
metamon.egg-info/SOURCES.txt
metamon.egg-info/dependency_links.txt
metamon.egg-info/not-zip-safe
metamon.egg-info/requires.txt
metamon.egg-info/top_level.txt