Metadata-Version: 1.1
Name: metamon
Version: 0.1.1
Summary: Procuce metadata for your data
Home-page: http://github.com/knowru/metamon
Author: Ken Park
Author-email: spark@example.com
License: MIT
Keywords: metadata,descriptive analytics
Platform: UNKNOWN
Classifier: Development Status :: 5 - Production/Stable
Classifier: License :: OSI Approved :: MIT License
Classifier: Programming Language :: Python :: 3.6
Classifier: Topic :: Scientific/Engineering :: Information Analysis
